serl/__init__.py
serl/__main__.py
serl/config.py
serl/constants.py
serl/highlight.py
serl/lexer.py
serl/logger.py
serl/main.py
serl/parser.py
serl/schema.py
serl/utils.py
serl-0.3.0b0.dist-info/LICENSE
serl-0.3.0b0.dist-info/METADATA
serl-0.3.0b0.dist-info/WHEEL
serl-0.3.0b0.dist-info/entry_points.txt
serl-0.3.0b0.dist-info/top_level.txt
serl-0.3.0b0.dist-info/RECORD
