Metadata-Version: 2.1
Name: serl
Version: 0.3.0b0
Summary: Serl - A tool for creating and using languages
Author: Harry Downing
Author-email: harry.downing17@gmail.com
License: MIT
Project-URL: Repository, https://github.com/harrydowning/serl
Project-URL: Documentation, https://serl.readthedocs.io/en/latest/index.html
Classifier: Programming Language :: Python :: 3
Classifier: License :: OSI Approved :: MIT License
Classifier: Operating System :: OS Independent
Requires-Python: >=3.11
License-File: LICENSE
Requires-Dist: PyYAML
Requires-Dist: docopt
Requires-Dist: ply (==3.11)
Requires-Dist: regex
Requires-Dist: networkx
Requires-Dist: jsonschema
Requires-Dist: Pygments
Requires-Dist: Pillow
Requires-Dist: requests
